dags
kueri
