Metadata-Version: 2.1
Name: kueri
Version: 0.5.2
Summary: Helper scripts for CI pipeline operations
Home-page: https://gitlab.mapan.io/data-eng/kueri
Author: DE Team
Author-email: data.eng@ruma.co.id
License: MIT
Platform: UNKNOWN
Classifier: License :: OSI Approved :: MIT License
Classifier: Programming Language :: Python
Classifier: Programming Language :: Python :: 3
Classifier: Programming Language :: Python :: 3.6
Classifier: Programming Language :: Python :: Implementation :: CPython
Classifier: Programming Language :: Python :: Implementation :: PyPy
Requires-Python: >=3.4.0
